parallel_wget.py
parallel_wget-0.0.11.dist-info/DESCRIPTION.rst
parallel_wget-0.0.11.dist-info/LICENSE.txt
parallel_wget-0.0.11.dist-info/METADATA
parallel_wget-0.0.11.dist-info/RECORD
parallel_wget-0.0.11.dist-info/WHEEL
parallel_wget-0.0.11.dist-info/metadata.json
parallel_wget-0.0.11.dist-info/top_level.txt
